<?xml version="1.0" encoding="UTF-8"?>
<site>
   <description url="http://run-jetty-run.googlecode.com">
      run-jetty-run Eclipse plugin
   </description>
   <feature url="features/runjettyrun_feature_1.0.0.jar" id="runjettyrun_feature" version="1.0.0">
      <category name="RunJettyRun 1.0"/>
   </feature>
   <feature url="features/runjettyrun_feature_1.0.1.jar" id="runjettyrun_feature" version="1.0.1">
      <category name="RunJettyRun 1.0"/>
   </feature>
   <feature url="features/runjettyrun_feature_1.1.0.jar" id="runjettyrun_feature" version="1.1.0">
      <category name="RunJettyRun 1.1"/>
   </feature>
   <feature url="features/runjettyrun_feature_1.1.1.jar" id="runjettyrun_feature" version="1.1.1">
      <category name="RunJettyRun 1.1"/>
   </feature>
   <feature url="features/runjettyrun_feature_1.2.0.jar" id="runjettyrun_feature" version="1.2">
      <category name="RunJettyRun 1.2"/>
   </feature>
   <feature url="features/runjettyrun_feature_1.2.1.jar" id="runjettyrun_feature" version="1.2.1">
      <category name="RunJettyRun 1.2"/>
   </feature>
   <feature url="features/runjettyrun_feature_1.2.1.1.jar" id="runjettyrun_feature" version="1.2.1.1">
      <category name="RunJettyRun 1.2"/>
   </feature>
   <feature url="features/runjettyrun_feature_1.2.2.jar" id="runjettyrun_feature" version="1.2.2">
      <category name="RunJettyRun 1.2"/>
   </feature>
   <feature url="features/runjettyrun_feature_1.2.2.1.jar" id="runjettyrun_feature" version="1.2.2.1">
      <category name="RunJettyRun 1.2"/>
   </feature>
   <feature url="features/runjettyrun_feature_1.3.0.jar" id="runjettyrun_feature" version="1.3.0">
      <category name="RunJettyRun 1.3"/>
   </feature>
   <feature url="features/runjettyrun_feature_support_jetty7_1.3.0.jar" id="runjettyrun_feature_support_jetty7" version="1.3.0">
      <category name="RunJettyRun 1.3"/>
   </feature>
   <feature url="features/runjettyrun_feature_support_jetty8_1.3.0.jar" id="runjettyrun_feature_support_jetty8" version="1.3.0">
      <category name="RunJettyRun 1.3"/>
   </feature>
   <feature url="features/runjettyrun_feature_support_jetty7_1.3.0.1.jar" id="runjettyrun_feature_support_jetty7" version="1.3.0.1">
      <category name="RunJettyRun 1.3"/>
   </feature>
   <feature url="features/runjettyrun_feature_support_jetty8_1.3.0.1.jar" id="runjettyrun_feature_support_jetty8" version="1.3.0.1">
      <category name="RunJettyRun 1.3"/>
   </feature>
   <category-def name="RunJettyRun 1.2" label="RunJettyRun 1.2"/>
   <category-def name="RunJettyRun 1.1" label="RunJettyRun 1.1"/>
   <category-def name="RunJettyRun 1.0" label="RunJettyRun 1.0"/>
   <category-def name="RunJettyRun 1.3" label="RunJettyRun 1.3"/>
</site>
